{
  "preprocessing": [
    {
      "fl": "sng",
      "smallx": 1.1189789772033691,
      "largex": 2.4974498748779297,
      "trainable": false
    },
    {
      "fl": "g",
      "smallx": 1.019212007522583,
      "largex": 5.401485443115234,
      "trainable": false
    },
    {
      "fl": "v",
      "smallx": 0.7207998633384705,
      "largex": 1.8982924222946167,
      "trainable": false
    },
    {
      "fl": "v3",
      "smallx": 0.28716540336608887,
      "largex": 2.0122146606445312,
      "trainable": false
    },
    {
      "fl": "v8",
      "smallx": 0.6588207483291626,
      "largex": 2.790492057800293,
      "trainable": false
    },
    {
      "fl": "t3",
      "smallx": 0.39691635966300964,
      "largex": 2.041628360748291,
      "trainable": false
    },
    {
      "fl": "t8",
      "smallx": 0.7025141716003418,
      "largex": 3.1668858528137207,
      "trainable": false
    },
    {
      "fl": "t15",
      "smallx": 1.1134644746780396,
      "largex": 1.8647302389144897,
      "trainable": false
    }
  ],
  "stop_epoch": 12915,
  "best_epoch": 11213,
  "erf_tr": 2.2459521293640137,
  "erf_vl": 2.3997416496276855,
  "chi2": 1.269161581993103,
  "pos_state": "POS_PASS",
  "arc_lengths": [
    1.2213836249197958,
    1.077853696755525,
    1.1847232453671697,
    1.0306766945555905,
    1.1616307276910225
  ],
  "integrability": [
    0.002461516502080152,
    0.002461516502080152,
    1.1879043001150613e-05,
    0.029160323552787082,
    0.0051640492165472285
  ],
  "timing": {
    "walltime": {
      "Total": 1987.3865065574646,
      "start": 0.0,
      "replica_set": 0.19756650924682617,
      "replica_fitted": 1987.386328458786,
      "replica_set_to_replica_fitted": 1987.1887619495392
    },
    "cputime": {
      "Total": 3559.624136776,
      "start": 0.0,
      "replica_set": 0.17916001800000458,
      "replica_fitted": 3559.623955486,
      "replica_set_to_replica_fitted": 3559.444795468
    }
  },
  "version": {
    "numpy": "1.26.4",
    "nnpdf": "4.0.10",
    "validphys": "4.0.10"
  }
}
